[
  {
    "title": "Harry Potter and the Sorcerer’s Stone",
    "content": "A tale of hope, challenge, and personal transformation.",
    "price": 11.99,
    "category": "Fantasy",
    "rating": 4.8,
    "isbn": "9781134572938",
    "author": "J.K. Rowling",
    "pages": 345,
    "publication_year": 1997,
    "description": "A profound and moving narrative exploring human resilience, choices, and transformation."
  },
  {
    "title": "To Kill a Mockingbird",
    "content": "Dark secrets threaten the balance of an entire society.",
    "price": 9.50,
    "category": "Classic",
    "rating": 4.9,
    "isbn": "9781409238451",
    "author": "Harper Lee",
    "pages": 324,
    "publication_year": 1960,
    "description": "This novel explores the intricacies of society, love, and personal awakening."
  },
  {
    "title": "1984",
    "content": "Dystopian world controlled by technology and fear.",
    "price": 10.25,
    "category": "Dystopian",
    "rating": 4.7,
    "isbn": "9783145692136",
    "author": "George Orwell",
    "pages": 328,
    "publication_year": 1949,
    "description": "An unforgettable journey through inner conflict and societal challenges."
  },
  {
    "title": "The Hobbit",
    "content": "Explores the depth of human emotions and relationships.",
    "price": 10.99,
    "category": "Fantasy",
    "rating": 4.8,
    "isbn": "9785931204872",
    "author": "J.R.R. Tolkien",
    "pages": 310,
    "publication_year": 1937,
    "description": "An epic tale of destiny, resistance, and the search for meaning in chaos."
  },
  {
    "title": "Pride and Prejudice",
    "content": "Magical elements entwined with profound life lessons.",
    "price": 8.99,
    "category": "Romance",
    "rating": 4.6,
    "isbn": "9781058394831",
    "author": "Jane Austen",
    "pages": 279,
    "publication_year": 1813,
    "description": "Richly layered with symbolism, it dissects the complexities of the human condition."
  },
  {
    "title": "Dune",
    "content": "A gripping narrative of power, love, and consequences.",
    "price": 12.99,
    "category": "Sci-Fi",
    "rating": 4.5,
    "isbn": "9782315647283",
    "author": "Frank Herbert",
    "pages": 412,
    "publication_year": 1965,
    "description": "A brilliant blend of reality and imagination, infused with philosophical undertones."
  },
  {
    "title": "Catch-22",
    "content": "Battle between tradition and progress shapes the journey.",
    "price": 9.75,
    "category": "Satire",
    "rating": 4.4,
    "isbn": "9785938046723",
    "author": "Joseph Heller",
    "pages": 453,
    "publication_year": 1961,
    "description": "Dark, gripping, and thought-provoking, it questions morality and free will."
  },
  {
    "title": "The Catcher in the Rye",
    "content": "Unravels mysteries in an unpredictable setting.",
    "price": 8.99,
    "category": "Classic",
    "rating": 4.1,
    "isbn": "9784021583247",
    "author": "J.D. Salinger",
    "pages": 277,
    "publication_year": 1951,
    "description": "A masterful work that blurs the line between truth and illusion."
  },
  {
    "title": "The Alchemist",
    "content": "Explores the depth of human emotions and relationships.",
    "price": 10.49,
    "category": "Philosophical Fiction",
    "rating": 4.3,
    "isbn": "9782034582935",
    "author": "Paulo Coelho",
    "pages": 197,
    "publication_year": 1988,
    "description": "A compelling story of ambition, regret, and redemption told with vivid prose."
  },
  {
    "title": "One Hundred Years of Solitude",
    "content": "Magical elements entwined with profound life lessons.",
    "price": 12.49,
    "category": "Magical Realism",
    "rating": 4.6,
    "isbn": "9784938294752",
    "author": "Gabriel García Márquez",
    "pages": 417,
    "publication_year": 1967,
    "description": "Explores themes of identity, power, and the fragile nature of freedom."
  },
  {
    "title": "Moby-Dick",
    "content": "Dark secrets threaten the balance of an entire society.",
    "price": 10.99,
    "category": "Adventure",
    "rating": 4.0,
    "isbn": "9785923748294",
    "author": "Herman Melville",
    "pages": 635,
    "publication_year": 1851,
    "description": "A profound and moving narrative exploring human resilience, choices, and transformation."
  },
  {
    "title": "War and Peace",
    "content": "An epic tale of destiny, resistance, and the search for meaning in chaos.",
    "price": 13.95,
    "category": "Historical",
    "rating": 4.7,
    "isbn": "9785839274618",
    "author": "Leo Tolstoy",
    "pages": 1225,
    "publication_year": 1869,
    "description": "This novel explores the intricacies of society, love, and personal awakening."
  },
  {
    "title": "The Great Gatsby",
    "content": "A tale of hope, challenge, and personal transformation.",
    "price": 9.75,
    "category": "Classic",
    "rating": 4.3,
    "isbn": "9781839472187",
    "author": "F. Scott Fitzgerald",
    "pages": 218,
    "publication_year": 1925,
    "description": "An unforgettable journey through inner conflict and societal challenges."
  },
  {
    "title": "Jane Eyre",
    "content": "Unravels mysteries in an unpredictable setting.",
    "price": 9.45,
    "category": "Romance",
    "rating": 4.5,
    "isbn": "9782047359284",
    "author": "Charlotte Brontë",
    "pages": 507,
    "publication_year": 1847,
    "description": "Richly layered with symbolism, it dissects the complexities of the human condition."
  },
  {
    "title": "The Lord of the Rings",
    "content": "Dark secrets threaten the balance of an entire society.",
    "price": 22.99,
    "category": "Fantasy",
    "rating": 4.9,
    "isbn": "9781928471236",
    "author": "J.R.R. Tolkien",
    "pages": 1178,
    "publication_year": 1954,
    "description": "A brilliant blend of reality and imagination, infused with philosophical undertones."
  },
  {
    "title": "Brave New World",
    "content": "A gripping narrative of power, love, and consequences.",
    "price": 9.89,
    "category": "Dystopian",
    "rating": 4.2,
    "isbn": "9781504932748",
    "author": "Aldous Huxley",
    "pages": 268,
    "publication_year": 1932,
    "description": "Dark, gripping, and thought-provoking, it questions morality and free will."
  },
  {
    "title": "Animal Farm",
    "content": "Dystopian world controlled by technology and fear.",
    "price": 7.99,
    "category": "Political Fiction",
    "rating": 4.6,
    "isbn": "9783859271836",
    "author": "George Orwell",
    "pages": 112,
    "publication_year": 1945,
    "description": "A masterful work that blurs the line between truth and illusion."
  },
  {
    "title": "The Chronicles of Narnia",
    "content": "Explores the depth of human emotions and relationships.",
    "price": 19.95,
    "category": "Fantasy",
    "rating": 4.7,
    "isbn": "9782763184513",
    "author": "C.S. Lewis",
    "pages": 767,
    "publication_year": 1956,
    "description": "A compelling story of ambition, regret, and redemption told with vivid prose."
  },
  {
    "title": "The Little Prince",
    "content": "A gripping narrative of power, love, and consequences.",
    "price": 8.99,
    "category": "Philosophical Fiction",
    "rating": 4.5,
    "isbn": "9783027842914",
    "author": "Antoine de Saint-Exupéry",
    "pages": 96,
    "publication_year": 1943,
    "description": "Explores themes of identity, power, and the fragile nature of freedom."
  },
  {
    "title": "Frankenstein",
    "content": "Magical elements entwined with profound life lessons.",
    "price": 9.49,
    "category": "Horror",
    "rating": 4.3,
    "isbn": "9782148731546",
    "author": "Mary Shelley",
    "pages": 280,
    "publication_year": 1818,
    "description": "A profound and moving narrative exploring human resilience, choices, and transformation."
  },
  {
    "title": "Crime and Punishment",
    "content": "Explores the depth of human emotions and relationships.",
    "price": 11.99,
    "category": "Classic",
    "rating": 4.7,
    "isbn": "9781402846932",
    "author": "Fyodor Dostoevsky",
    "pages": 671,
    "publication_year": 1866,
    "description": "An unforgettable journey through inner conflict and societal challenges."
  },
  {
    "title": "The Odyssey",
    "content": "Dark secrets threaten the balance of an entire society.",
    "price": 10.50,
    "category": "Classic",
    "rating": 4.4,
    "isbn": "9783041581728",
    "author": "Homer",
    "pages": 541,
    "publication_year": -800,
    "description": "This novel explores the intricacies of society, love, and personal awakening."
  },
  {
    "title": "The Iliad",
    "content": "A tale of hope, challenge, and personal transformation.",
    "price": 10.50,
    "category": "Classic",
    "rating": 4.4,
    "isbn": "9781905271482",
    "author": "Homer",
    "pages": 683,
    "publication_year": -762,
    "description": "A brilliant blend of reality and imagination, infused with philosophical undertones."
  },
  {
    "title": "Wuthering Heights",
    "content": "Unravels mysteries in an unpredictable setting.",
    "price": 9.25,
    "category": "Romance",
    "rating": 4.2,
    "isbn": "9781023857491",
    "author": "Emily Brontë",
    "pages": 313,
    "publication_year": 1847,
    "description": "Richly layered with symbolism, it dissects the complexities of the human condition."
  },
  {
    "title": "Great Expectations",
    "content": "Dark secrets threaten the balance of an entire society.",
    "price": 10.49,
    "category": "Classic",
    "rating": 4.3,
    "isbn": "9781092837461",
    "author": "Charles Dickens",
    "pages": 505,
    "publication_year": 1861,
    "description": "A compelling story of ambition, regret, and redemption told with vivid prose."
  },
  {
    "title": "Les Misérables",
    "content": "A gripping narrative of power, love, and consequences.",
    "price": 12.99,
    "category": "Historical",
    "rating": 4.7,
    "isbn": "9781183958215",
    "author": "Victor Hugo",
    "pages": 1463,
    "publication_year": 1862,
    "description": "An epic tale of destiny, resistance, and the search for meaning in chaos."
  },
  {
    "title": "The Brothers Karamazov",
    "content": "Magical elements entwined with profound life lessons.",
    "price": 11.95,
    "category": "Classic",
    "rating": 4.6,
    "isbn": "9781205839284",
    "author": "Fyodor Dostoevsky",
    "pages": 824,
    "publication_year": 1880,
    "description": "Richly layered with symbolism, it dissects the complexities of the human condition."
  },
  {
    "title": "Anna Karenina",
    "content": "Explores the depth of human emotions and relationships.",
    "price": 10.99,
    "category": "Romance",
    "rating": 4.5,
    "isbn": "9781038492728",
    "author": "Leo Tolstoy",
    "pages": 964,
    "publication_year": 1878,
    "description": "This novel explores the intricacies of society, love, and personal awakening."
  },
  {
    "title": "Don Quixote",
    "content": "A tale of hope, challenge, and personal transformation.",
    "price": 12.25,
    "category": "Classic",
    "rating": 4.4,
    "isbn": "9781092847381",
    "author": "Miguel de Cervantes",
    "pages": 1072,
    "publication_year": 1605,
    "description": "A brilliant blend of reality and imagination, infused with philosophical undertones."
  },
  {
    "title": "Madame Bovary",
    "content": "Dark secrets threaten the balance of an entire society.",
    "price": 9.80,
    "category": "Romance",
    "rating": 4.1,
    "isbn": "9781150384572",
    "author": "Gustave Flaubert",
    "pages": 328,
    "publication_year": 1856,
    "description": "A profound and moving narrative exploring human resilience, choices, and transformation."
  },
  {
    "title": "A Tale of Two Cities",
    "content": "Battle between tradition and progress shapes the journey.",
    "price": 9.49,
    "category": "Historical",
    "rating": 4.5,
    "isbn": "9781248492039",
    "author": "Charles Dickens",
    "pages": 489,
    "publication_year": 1859,
    "description": "An unforgettable journey through inner conflict and societal challenges."
  },
  {
    "title": "Ulysses",
    "content": "Unravels mysteries in an unpredictable setting.",
    "price": 12.49,
    "category": "Literary Fiction",
    "rating": 4.2,
    "isbn": "9781937482941",
    "author": "James Joyce",
    "pages": 730,
    "publication_year": 1922,
    "description": "A masterful work that blurs the line between truth and illusion."
  },
  {
    "title": "The Divine Comedy",
    "content": "Dystopian world controlled by technology and fear.",
    "price": 13.95,
    "category": "Classic",
    "rating": 4.8,
    "isbn": "9781429483792",
    "author": "Dante Alighieri",
    "pages": 798,
    "publication_year": 1320,
    "description": "Explores themes of identity, power, and the fragile nature of freedom."
  },
  {
    "title": "Lolita",
    "content": "Magical elements entwined with profound life lessons.",
    "price": 9.95,
    "category": "Classic",
    "rating": 4.2,
    "isbn": "9781092839182",
    "author": "Vladimir Nabokov",
    "pages": 336,
    "publication_year": 1955,
    "description": "Dark, gripping, and thought-provoking, it questions morality and free will."
  },
  {
    "title": "Beloved",
    "content": "A gripping narrative of power, love, and consequences.",
    "price": 10.49,
    "category": "Historical",
    "rating": 4.5,
    "isbn": "9781102849372",
    "author": "Toni Morrison",
    "pages": 324,
    "publication_year": 1987,
    "description": "A brilliant blend of reality and imagination, infused with philosophical undertones."
  },
  {
    "title": "The Grapes of Wrath",
    "content": "Unravels mysteries in an unpredictable setting.",
    "price": 9.75,
    "category": "Historical",
    "rating": 4.6,
    "isbn": "9781293857193",
    "author": "John Steinbeck",
    "pages": 464,
    "publication_year": 1939,
    "description": "A compelling story of ambition, regret, and redemption told with vivid prose."
  },
  {
    "title": "Invisible Man",
    "content": "Explores the depth of human emotions and relationships.",
    "price": 11.29,
    "category": "Literary Fiction",
    "rating": 4.4,
    "isbn": "9781194839272",
    "author": "Ralph Ellison",
    "pages": 581,
    "publication_year": 1952,
    "description": "This novel explores the intricacies of society, love, and personal awakening."
  },
  {
    "title": "Slaughterhouse-Five",
    "content": "A tale of hope, challenge, and personal transformation.",
    "price": 9.49,
    "category": "Satire",
    "rating": 4.3,
    "isbn": "9781184728392",
    "author": "Kurt Vonnegut",
    "pages": 275,
    "publication_year": 1969,
    "description": "A profound and moving narrative exploring human resilience, choices, and transformation."
  },
  {
    "title": "The Sound and the Fury",
    "content": "Dark secrets threaten the balance of an entire society.",
    "price": 10.99,
    "category": "Classic",
    "rating": 4.0,
    "isbn": "9781394738262",
    "author": "William Faulkner",
    "pages": 326,
    "publication_year": 1929,
    "description": "An unforgettable journey through inner conflict and societal challenges."
  },
  {
    "title": "One Flew Over the Cuckoo’s Nest",
    "content": "Magical elements entwined with profound life lessons.",
    "price": 9.89,
    "category": "Psychological Fiction",
    "rating": 4.5,
    "isbn": "9781294839281",
    "author": "Ken Kesey",
    "pages": 312,
    "publication_year": 1962,
    "description": "Richly layered with symbolism, it dissects the complexities of the human condition."
  },
  {
    "title": "On the Road",
    "content": "Battle between tradition and progress shapes the journey.",
    "price": 8.95,
    "category": "Literary Fiction",
    "rating": 4.1,
    "isbn": "9781393847582",
    "author": "Jack Kerouac",
    "pages": 320,
    "publication_year": 1957,
    "description": "A brilliant blend of reality and imagination, infused with philosophical undertones."
  },
  {
    "title": "The Stranger",
    "content": "Dystopian world controlled by technology and fear.",
    "price": 9.75,
    "category": "Philosophical Fiction",
    "rating": 4.3,
    "isbn": "9781148293847",
    "author": "Albert Camus",
    "pages": 123,
    "publication_year": 1942,
    "description": "Dark, gripping, and thought-provoking, it questions morality and free will."
  },
  {
    "title": "Heart of Darkness",
    "content": "Unravels mysteries in an unpredictable setting.",
    "price": 8.49,
    "category": "Classic",
    "rating": 4.2,
    "isbn": "9781048393728",
    "author": "Joseph Conrad",
    "pages": 96,
    "publication_year": 1899,
    "description": "A masterful work that blurs the line between truth and illusion."
  },
  {
    "title": "Fahrenheit 451",
    "content": "Explores the depth of human emotions and relationships.",
    "price": 9.29,
    "category": "Dystopian",
    "rating": 4.5,
    "isbn": "9781195838492",
    "author": "Ray Bradbury",
    "pages": 194,
    "publication_year": 1953,
    "description": "Explores themes of identity, power, and the fragile nature of freedom."
  },
  {
    "title": "The Road",
    "content": "Dark secrets threaten the balance of an entire society.",
    "price": 10.99,
    "category": "Post-Apocalyptic",
    "rating": 4.4,
    "isbn": "9781394739182",
    "author": "Cormac McCarthy",
    "pages": 287,
    "publication_year": 2006,
    "description": "A profound and moving narrative exploring human resilience, choices, and transformation."
  },
  {
    "title": "Life of Pi",
    "content": "A gripping narrative of power, love, and consequences.",
    "price": 9.85,
    "category": "Adventure",
    "rating": 4.6,
    "isbn": "9781138493726",
    "author": "Yann Martel",
    "pages": 319,
    "publication_year": 2001,
    "description": "A compelling story of ambition, regret, and redemption told with vivid prose."
  },

  {
    "title": "The Kite Runner",
    "content": "Explores the depth of human emotions and relationships.",
    "price": 10.49,
    "category": "Historical Fiction",
    "rating": 4.7,
    "isbn": "9781405837483",
    "author": "Khaled Hosseini",
    "pages": 371,
    "publication_year": 2003,
    "description": "A compelling story of ambition, regret, and redemption told with vivid prose."
  },
  {
    "title": "A Thousand Splendid Suns",
    "content": "Dark secrets threaten the balance of an entire society.",
    "price": 10.99,
    "category": "Historical Fiction",
    "rating": 4.6,
    "isbn": "9781092383748",
    "author": "Khaled Hosseini",
    "pages": 384,
    "publication_year": 2007,
    "description": "An unforgettable journey through inner conflict and societal challenges."
  },
  {
    "title": "The Book Thief",
    "content": "A tale of hope, challenge, and personal transformation.",
    "price": 9.49,
    "category": "Historical Fiction",
    "rating": 4.7,
    "isbn": "9781038493748",
    "author": "Markus Zusak",
    "pages": 552,
    "publication_year": 2005,
    "description": "This novel explores the intricacies of society, love, and personal awakening."
  },
  {
    "title": "The Fault in Our Stars",
    "content": "Magical elements entwined with profound life lessons.",
    "price": 8.95,
    "category": "Young Adult",
    "rating": 4.4,
    "isbn": "9781205837482",
    "author": "John Green",
    "pages": 313,
    "publication_year": 2012,
    "description": "A profound and moving narrative exploring human resilience, choices, and transformation."
  },
  {
    "title": "Looking for Alaska",
    "content": "Dystopian world controlled by technology and fear.",
    "price": 8.75,
    "category": "Young Adult",
    "rating": 4.2,
    "isbn": "9781138493849",
    "author": "John Green",
    "pages": 221,
    "publication_year": 2005,
    "description": "Richly layered with symbolism, it dissects the complexities of the human condition."
  },
  {
    "title": "Paper Towns",
    "content": "Unravels mysteries in an unpredictable setting.",
    "price": 8.99,
    "category": "Young Adult",
    "rating": 4.1,
    "isbn": "9781205849384",
    "author": "John Green",
    "pages": 305,
    "publication_year": 2008,
    "description": "A masterful work that blurs the line between truth and illusion."
  },
  {
    "title": "Thirteen Reasons Why",
    "content": "Battle between tradition and progress shapes the journey.",
    "price": 9.25,
    "category": "Young Adult",
    "rating": 4.3,
    "isbn": "9781305838471",
    "author": "Jay Asher",
    "pages": 288,
    "publication_year": 2007,
    "description": "Dark, gripping, and thought-provoking, it questions morality and free will."
  },
  {
    "title": "Eleanor & Park",
    "content": "Magical elements entwined with profound life lessons.",
    "price": 9.45,
    "category": "Romance",
    "rating": 4.4,
    "isbn": "9781394738213",
    "author": "Rainbow Rowell",
    "pages": 328,
    "publication_year": 2012,
    "description": "Explores themes of identity, power, and the fragile nature of freedom."
  },
  {
    "title": "Fangirl",
    "content": "A gripping narrative of power, love, and consequences.",
    "price": 9.85,
    "category": "Young Adult",
    "rating": 4.2,
    "isbn": "9781094839273",
    "author": "Rainbow Rowell",
    "pages": 445,
    "publication_year": 2013,
    "description": "A brilliant blend of reality and imagination, infused with philosophical undertones."
  },
  {
    "title": "Carry On",
    "content": "Explores the depth of human emotions and relationships.",
    "price": 10.29,
    "category": "Fantasy",
    "rating": 4.3,
    "isbn": "9781137482910",
    "author": "Rainbow Rowell",
    "pages": 522,
    "publication_year": 2015,
    "description": "A compelling story of ambition, regret, and redemption told with vivid prose."
  },
  {
    "title": "The Midnight Library",
    "content": "Dark secrets threaten the balance of an entire society.",
    "price": 11.10,
    "category": "Philosophical Fiction",
    "rating": 4.5,
    "isbn": "9781392938471",
    "author": "Matt Haig",
    "pages": 304,
    "publication_year": 2020,
    "description": "An unforgettable journey through inner conflict and societal challenges."
  },
  {
    "title": "Before the Coffee Gets Cold",
    "content": "Dystopian world controlled by technology and fear.",
    "price": 9.75,
    "category": "Fantasy",
    "rating": 4.3,
    "isbn": "9781293847582",
    "author": "Toshikazu Kawaguchi",
    "pages": 272,
    "publication_year": 2015,
    "description": "This novel explores the intricacies of society, love, and personal awakening."
  },
  {
    "title": "The Seven Husbands of Evelyn Hugo",
    "content": "A tale of hope, challenge, and personal transformation.",
    "price": 10.95,
    "category": "Drama",
    "rating": 4.7,
    "isbn": "9781203947582",
    "author": "Taylor Jenkins Reid",
    "pages": 385,
    "publication_year": 2017,
    "description": "A brilliant blend of reality and imagination, infused with philosophical undertones."
  },
  {
    "title": "Daisy Jones & The Six",
    "content": "Unravels mysteries in an unpredictable setting.",
    "price": 11.45,
    "category": "Contemporary",
    "rating": 4.5,
    "isbn": "9781183849283",
    "author": "Taylor Jenkins Reid",
    "pages": 368,
    "publication_year": 2019,
    "description": "A masterful work that blurs the line between truth and illusion."
  },
  {
    "title": "Malibu Rising",
    "content": "Explores the depth of human emotions and relationships.",
    "price": 10.75,
    "category": "Drama",
    "rating": 4.4,
    "isbn": "9781092838473",
    "author": "Taylor Jenkins Reid",
    "pages": 384,
    "publication_year": 2021,
    "description": "A profound and moving narrative exploring human resilience, choices, and transformation."
  },
  {
    "title": "It Ends With Us",
    "content": "Magical elements entwined with profound life lessons.",
    "price": 9.95,
    "category": "Romance",
    "rating": 4.6,
    "isbn": "9781092834738",
    "author": "Colleen Hoover",
    "pages": 384,
    "publication_year": 2016,
    "description": "Dark, gripping, and thought-provoking, it questions morality and free will."
  },
  {
    "title": "It Starts With Us",
    "content": "A gripping narrative of power, love, and consequences.",
    "price": 10.35,
    "category": "Romance",
    "rating": 4.5,
    "isbn": "9781394838271",
    "author": "Colleen Hoover",
    "pages": 336,
    "publication_year": 2022,
    "description": "A compelling story of ambition, regret, and redemption told with vivid prose."
  },
  {
    "title": "Ugly Love",
    "content": "Battle between tradition and progress shapes the journey.",
    "price": 9.25,
    "category": "Romance",
    "rating": 4.4,
    "isbn": "9781239483728",
    "author": "Colleen Hoover",
    "pages": 324,
    "publication_year": 2014,
    "description": "An unforgettable journey through inner conflict and societal challenges."
  },
  {
    "title": "Verity",
    "content": "Unravels mysteries in an unpredictable setting.",
    "price": 10.85,
    "category": "Thriller",
    "rating": 4.7,
    "isbn": "9781305839472",
    "author": "Colleen Hoover",
    "pages": 336,
    "publication_year": 2018,
    "description": "Explores themes of identity, power, and the fragile nature of freedom."
  },
  {
    "title": "Reminders of Him",
    "content": "Dystopian world controlled by technology and fear.",
    "price": 10.49,
    "category": "Romance",
    "rating": 4.3,
    "isbn": "9781057384952",
    "author": "Colleen Hoover",
    "pages": 335,
    "publication_year": 2022,
    "description": "A brilliant blend of reality and imagination, infused with philosophical undertones."
  },


  {
    "title": "The Silent Patient",
    "content": "Unravels mysteries in an unpredictable setting.",
    "price": 10.25,
    "category": "Thriller",
    "rating": 4.5,
    "isbn": "9781393848292",
    "author": "Alex Michaelides",
    "pages": 336,
    "publication_year": 2019,
    "description": "Dark, gripping, and thought-provoking, it questions morality and free will."
  },
  {
    "title": "The Guest List",
    "content": "A gripping narrative of power, love, and consequences.",
    "price": 9.95,
    "category": "Mystery",
    "rating": 4.3,
    "isbn": "9781039384728",
    "author": "Lucy Foley",
    "pages": 320,
    "publication_year": 2020,
    "description": "A masterful work that blurs the line between truth and illusion."
  },
  {
    "title": "The Paris Library",
    "content": "Magical elements entwined with profound life lessons.",
    "price": 11.10,
    "category": "Historical Fiction",
    "rating": 4.4,
    "isbn": "9781293849281",
    "author": "Janet Skeslien Charles",
    "pages": 368,
    "publication_year": 2021,
    "description": "A profound and moving narrative exploring human resilience, choices, and transformation."
  },
  {
    "title": "The Night Circus",
    "content": "Explores the depth of human emotions and relationships.",
    "price": 10.75,
    "category": "Fantasy",
    "rating": 4.5,
    "isbn": "9781058471839",
    "author": "Erin Morgenstern",
    "pages": 387,
    "publication_year": 2011,
    "description": "This novel explores the intricacies of society, love, and personal awakening."
  },
  {
    "title": "The House in the Cerulean Sea",
    "content": "Dystopian world controlled by technology and fear.",
    "price": 9.85,
    "category": "Fantasy",
    "rating": 4.7,
    "isbn": "9781305948371",
    "author": "TJ Klune",
    "pages": 394,
    "publication_year": 2020,
    "description": "A brilliant blend of reality and imagination, infused with philosophical undertones."
  },
  {
    "title": "Under the Whispering Door",
    "content": "Unravels mysteries in an unpredictable setting.",
    "price": 10.35,
    "category": "Fantasy",
    "rating": 4.4,
    "isbn": "9781038493848",
    "author": "TJ Klune",
    "pages": 373,
    "publication_year": 2021,
    "description": "Explores themes of identity, power, and the fragile nature of freedom."
  },
  {
    "title": "Circe",
    "content": "Magical elements entwined with profound life lessons.",
    "price": 10.99,
    "category": "Mythology",
    "rating": 4.6,
    "isbn": "9781204957384",
    "author": "Madeline Miller",
    "pages": 393,
    "publication_year": 2018,
    "description": "A compelling story of ambition, regret, and redemption told with vivid prose."
  },
  {
    "title": "The Song of Achilles",
    "content": "A tale of hope, challenge, and personal transformation.",
    "price": 10.49,
    "category": "Mythology",
    "rating": 4.8,
    "isbn": "9781184839284",
    "author": "Madeline Miller",
    "pages": 378,
    "publication_year": 2011,
    "description": "An unforgettable journey through inner conflict and societal challenges."
  },
  {
    "title": "Lore",
    "content": "Dark secrets threaten the balance of an entire society.",
    "price": 9.99,
    "category": "Fantasy",
    "rating": 4.2,
    "isbn": "9781304739281",
    "author": "Alexandra Bracken",
    "pages": 480,
    "publication_year": 2021,
    "description": "A brilliant blend of reality and imagination, infused with philosophical undertones."
  },
  {
    "title": "The Atlas Six",
    "content": "Battle between tradition and progress shapes the journey.",
    "price": 10.95,
    "category": "Fantasy",
    "rating": 4.5,
    "isbn": "9781104839472",
    "author": "Olivie Blake",
    "pages": 480,
    "publication_year": 2020,
    "description": "Richly layered with symbolism, it dissects the complexities of the human condition."
  },
  {
    "title": "The Love Hypothesis",
    "content": "A gripping narrative of power, love, and consequences.",
    "price": 10.45,
    "category": "Romance",
    "rating": 4.6,
    "isbn": "9781393847382",
    "author": "Ali Hazelwood",
    "pages": 384,
    "publication_year": 2021,
    "description": "This novel explores the intricacies of society, love, and personal awakening."
  },
  {
    "title": "People We Meet on Vacation",
    "content": "Explores the depth of human emotions and relationships.",
    "price": 9.75,
    "category": "Romance",
    "rating": 4.4,
    "isbn": "9781092849273",
    "author": "Emily Henry",
    "pages": 364,
    "publication_year": 2021,
    "description": "A compelling story of ambition, regret, and redemption told with vivid prose."
  },
  {
    "title": "Beach Read",
    "content": "Unravels mysteries in an unpredictable setting.",
    "price": 9.49,
    "category": "Romance",
    "rating": 4.3,
    "isbn": "9781059483726",
    "author": "Emily Henry",
    "pages": 384,
    "publication_year": 2020,
    "description": "A masterful work that blurs the line between truth and illusion."
  },
  {
    "title": "Book Lovers",
    "content": "A tale of hope, challenge, and personal transformation.",
    "price": 9.85,
    "category": "Romance",
    "rating": 4.5,
    "isbn": "9781393837483",
    "author": "Emily Henry",
    "pages": 384,
    "publication_year": 2022,
    "description": "Explores themes of identity, power, and the fragile nature of freedom."
  },
  {
    "title": "Fourth Wing",
    "content": "Magical elements entwined with profound life lessons.",
    "price": 11.99,
    "category": "Fantasy",
    "rating": 4.8,
    "isbn": "9781184728392",
    "author": "Rebecca Yarros",
    "pages": 512,
    "publication_year": 2023,
    "description": "A profound and moving narrative exploring human resilience, choices, and transformation."
  },
  {
    "title": "Iron Flame",
    "content": "Dark secrets threaten the balance of an entire society.",
    "price": 12.45,
    "category": "Fantasy",
    "rating": 4.7,
    "isbn": "9781205938471",
    "author": "Rebecca Yarros",
    "pages": 624,
    "publication_year": 2023,
    "description": "An unforgettable journey through inner conflict and societal challenges."
  },
  {
    "title": "The Measure",
    "content": "Dystopian world controlled by technology and fear.",
    "price": 10.99,
    "category": "Speculative Fiction",
    "rating": 4.4,
    "isbn": "9781305849382",
    "author": "Nikki Erlick",
    "pages": 368,
    "publication_year": 2022,
    "description": "A brilliant blend of reality and imagination, infused with philosophical undertones."
  },
  {
    "title": "Tomorrow, and Tomorrow, and Tomorrow",
    "content": "Unravels mysteries in an unpredictable setting.",
    "price": 11.25,
    "category": "Literary Fiction",
    "rating": 4.5,
    "isbn": "9781039483728",
    "author": "Gabrielle Zevin",
    "pages": 416,
    "publication_year": 2022,
    "description": "A masterful work that blurs the line between truth and illusion."
  },
  {
    "title": "Lessons in Chemistry",
    "content": "Explores the depth of human emotions and relationships.",
    "price": 10.49,
    "category": "Historical Fiction",
    "rating": 4.6,
    "isbn": "9781394837482",
    "author": "Bonnie Garmus",
    "pages": 400,
    "publication_year": 2022,
    "description": "A compelling story of ambition, regret, and redemption told with vivid prose."
  },
  {
    "title": "Remarkably Bright Creatures",
    "content": "Battle between tradition and progress shapes the journey.",
    "price": 10.85,
    "category": "Contemporary",
    "rating": 4.4,
    "isbn": "9781205839284",
    "author": "Shelby Van Pelt",
    "pages": 368,
    "publication_year": 2022,
    "description": "Dark, gripping, and thought-provoking, it questions morality and free will."
  },
  {
    "title": "None of This Is True",
    "content": "A gripping narrative of power, love, and consequences.",
    "price": 11.35,
    "category": "Thriller",
    "rating": 4.5,
    "isbn": "9781305839272",
    "author": "Lisa Jewell",
    "pages": 384,
    "publication_year": 2023,
    "description": "A brilliant blend of reality and imagination, infused with philosophical undertones."
  }
]
